Metadata-Version: 2.1
Name: aldServer
Version: 0.0.1
Summary: aldServer - a template server
Home-page: UNKNOWN
Author: Aldison Lluka
Author-email: aldison.lluka.al@gmail.com
License: UNKNOWN
Platform: UNKNOWN
Requires-Python: >=3
